pygyat/__init__.py
pygyat/glaze.py
pygyat/logger.py
pygyat/parser.py
pygyat-1.0.8.data/data/man/man1/gyat2py.1
pygyat-1.0.8.data/data/man/man1/py2gyat.1
pygyat-1.0.8.data/data/man/man1/pygyat.1
pygyat-1.0.8.data/scripts/gyat2py
pygyat-1.0.8.data/scripts/py2gyat
pygyat-1.0.8.data/scripts/pygyat
pygyat-1.0.8.dist-info/LICENSE
pygyat-1.0.8.dist-info/METADATA
pygyat-1.0.8.dist-info/WHEEL
pygyat-1.0.8.dist-info/top_level.txt
pygyat-1.0.8.dist-info/RECORD
