Metadata-Version: 2.1
Name: pygyat
Version: 1.0.8
Summary: Python with rizz
Home-page: https://github.com/shamith09/pygyat
Author: Shamith Pasula
Author-email: shamith09@berkeley.edu
License: MIT
License-File: LICENSE
